flake8_warnings/__init__.py
flake8_warnings/__main__.py
flake8_warnings/_cli.py
flake8_warnings/_finder.py
flake8_warnings/_flake8_plugin.py
flake8_warnings/_pylint_plugin.py
flake8_warnings/_extractors/__init__.py
flake8_warnings/_extractors/_base.py
flake8_warnings/_extractors/_decorators.py
flake8_warnings/_extractors/_docstrings.py
flake8_warnings/_extractors/_stdlib.py
flake8_warnings/_extractors/_warnings.py
flake8_warnings-0.4.1.dist-info/entry_points.txt
flake8_warnings-0.4.1.dist-info/LICENSE
flake8_warnings-0.4.1.dist-info/WHEEL
flake8_warnings-0.4.1.dist-info/METADATA
flake8_warnings-0.4.1.dist-info/RECORD
