Metadata-Version: 2.1
Name: flake8-warnings
Version: 0.4.1
Summary: Linter (flake8, pylint, custom CLI) for finding usage of deprecated functions.
Keywords: deprecation,flake8,pylint,warnings,linter,flakehell
Author-email: Gram <gram@orsinium.dev>
Requires-Python: >=3.6
Classifier: Development Status :: 5 - Production/Stable
Classifier: Environment :: Plugins
Classifier: Intended Audience :: Developers
Classifier: License :: OSI Approved :: MIT License
Classifier: Programming Language :: Python
Classifier: Topic :: Software Development
Classifier: Topic :: Software Development :: Quality Assurance
Requires-Dist: astroid>=3.0.0
Requires-Dist: flake8 ; extra == "lint"
Requires-Dist: flake8-length ; extra == "lint"
Requires-Dist: mypy ; extra == "lint"
Requires-Dist: isort ; extra == "lint"
Requires-Dist: unify ; extra == "lint"
Requires-Dist: pytest ; extra == "test"
Project-URL: Source, https://github.com/orsinium-labs/flake8-warnings
Provides-Extra: lint
Provides-Extra: test
